mbf_externals/__init__.py
mbf_externals/externals.py
mbf_externals/prebuild.py
mbf_externals/snpdiffrs.py
mbf_externals/util.py
mbf_externals/aligners/__init__.py
mbf_externals/aligners/base.py
mbf_externals/aligners/bbmap.py
mbf_externals/aligners/bowtie.py
mbf_externals/aligners/bwa.py
mbf_externals/aligners/salmon.py
mbf_externals/aligners/star.py
mbf_externals/aligners/subread.py
mbf_externals/fastq/__init__.py
mbf_externals/kent/__init__.py
mbf_externals/peak_callers/__init__.py
mbf_externals/peak_callers/peakzilla.py
mbf_externals/testing/__init__.py
mbf_externals/testing/fixtures.py
mbf_externals-0.3.dist-info/AUTHORS.rst
mbf_externals-0.3.dist-info/LICENSE.txt
mbf_externals-0.3.dist-info/METADATA
mbf_externals-0.3.dist-info/WHEEL
mbf_externals-0.3.dist-info/top_level.txt
mbf_externals-0.3.dist-info/RECORD
